{
  "MVP-001": "completed",
  "MVP-002": "completed",
  "MVP-003": "completed",
  "MVP-004": "completed",
  "MVP-005": "completed",
  "MVP-006": "completed",
  "MVP-007": "completed",
  "MVP-008": "completed",
  "MVP-009": "completed",
  "MVP-010": "completed",
  "MVP-011": "completed",
  "MVP-012": "completed",
  "MVP-013C": "completed_or_in_pr",
  "MVP-013D": "completed_or_reviewed",
  "MVP-014A": "completed",
  "MVP-014B": "completed_no_report_found",
  "MVP-014C": "completed_in_pr",
  "MVP-014D": "failed_no_retry",
  "MVP-014E": "completed",
  "MVP-014F": "completed",
  "MVP-014G": "completed_not_parseable",
  "MVP-014H": "completed",
  "MVP-014I": "blocked_strategy_tester_failed_before_ea",
  "MILESTONE-014-FAILURE-REVIEW": "completed_by_mvp_014e",
  "MT5_CLOSE_AFTER_REAL_RUN_POLICY": "completed",
  "BACKTEST_BUDGET_PRODUCT_POLICY": "completed",
  "MVP-014J": "completed",
  "MVP-014K": "blocked_terminal_contract",
  "MVP-014L": "recommended_next_after_terminal_contract_pass"
}
